united/__init__.py
united/united.py
united-0.1.5.dist-info/AUTHORS.rst
united-0.1.5.dist-info/LICENSE
united-0.1.5.dist-info/METADATA
united-0.1.5.dist-info/WHEEL
united-0.1.5.dist-info/top_level.txt
united-0.1.5.dist-info/RECORD
