Metadata-Version: 2.1
Name: united
Version: 0.1.5
Summary: A SI unit representation and conversion tool.
Home-page: https://github.com/emtpb/united/
Author: Kevin Koch
Author-email: kevink2@mail.uni-paderborn.de
License: BSD
Platform: UNKNOWN
Classifier: Development Status :: 2 - Pre-Alpha
Classifier: Intended Audience :: Science/Research
Classifier: License :: OSI Approved :: BSD License
Classifier: Programming Language :: Python :: 3
Classifier: Topic :: Scientific/Engineering
Requires-Python: >=3
License-File: LICENSE
License-File: AUTHORS.rst
